minions/__init__.py
minions/exceptions.py
minions/implementations.py
minions/interfaces.py
minions/shell.py
minions/types.py
minions/_internal/__init__.py
minions/_internal/_domain/__init__.py
minions/_internal/_domain/exceptions.py
minions/_internal/_domain/gru.py
minions/_internal/_domain/gru_result_types.py
minions/_internal/_domain/gru_shell.py
minions/_internal/_domain/gru_shell_bkp.py
minions/_internal/_domain/gru_shell_demo.py
minions/_internal/_domain/gru_shell_draft.py
minions/_internal/_domain/gru_shell_draft_bkp.py
minions/_internal/_domain/minion copy 2.py
minions/_internal/_domain/minion copy.py
minions/_internal/_domain/minion.py
minions/_internal/_domain/minion_step.py
minions/_internal/_domain/minion_workflow_context.py
minions/_internal/_domain/pipeline.py
minions/_internal/_domain/resource.py
minions/_internal/_domain/types.py
minions/_internal/_framework/__init__.py
minions/_internal/_framework/async_component.py
minions/_internal/_framework/async_lifecycle.py
minions/_internal/_framework/async_service.py
minions/_internal/_framework/logger.py
minions/_internal/_framework/logger_console.py
minions/_internal/_framework/logger_file.py
minions/_internal/_framework/logger_noop.py
minions/_internal/_framework/metrics.py
minions/_internal/_framework/metrics_constants.py
minions/_internal/_framework/metrics_interface.py
minions/_internal/_framework/metrics_noop.py
minions/_internal/_framework/metrics_prometheus.py
minions/_internal/_framework/state_store.py
minions/_internal/_framework/state_store_noop.py
minions/_internal/_framework/state_store_sqlite.py
minions/_internal/_framework/state_store_sqlite_old.py
minions/_internal/_utils/__init__.py
minions/_internal/_utils/get_class.py
minions/_internal/_utils/get_relative_module_path.py
minions/_internal/_utils/safe_cancel_task.py
minions/_internal/_utils/safe_create_task.py
minions/_internal/_utils/serialization.py
minions-0.0.2.dist-info/licenses/LICENSE
minions-0.0.2.dist-info/METADATA
minions-0.0.2.dist-info/WHEEL
minions-0.0.2.dist-info/top_level.txt
minions-0.0.2.dist-info/RECORD
