Metadata-Version: 2.4
Name: minions
Version: 0.0.2
Summary: Async-native orchestration framework — pre-0.1.0 and under active development.
Author: Chris
License: MIT License
Project-URL: Homepage, https://github.com/crios1/minions
Project-URL: Source, https://github.com/crios1/minions
Project-URL: Issues, https://github.com/crios1/minions/issues
Classifier: Development Status :: 2 - Pre-Alpha
Classifier: Programming Language :: Python :: 3
Classifier: License :: OSI Approved :: MIT License
Classifier: Operating System :: OS Independent
Requires-Python: >=3.10
License-File: LICENSE
Requires-Dist: aiosqlite>=0.19.0
Dynamic: license-file
